ncapi_client/client.py
ncapi_client/dataset.py
ncapi_client/job.py
ncapi_client/messages.py
ncapi_client/ncs.py
ncapi_client/prediction.py
ncapi_client/session.py
ncapi_client/trained_model.py
ncapi_client/training.py
ncapi_client/utils.py
ncapi_client-0.2.7.dist-info/LICENSE
ncapi_client-0.2.7.dist-info/METADATA
ncapi_client-0.2.7.dist-info/WHEEL
ncapi_client-0.2.7.dist-info/entry_points.txt
ncapi_client-0.2.7.dist-info/top_level.txt
ncapi_client-0.2.7.dist-info/RECORD
