Metadata-Version: 2.1
Name: ncapi-client
Version: 0.2.7
Summary: Python client for NCAPI
Home-page: UNKNOWN
License: UNKNOWN
Platform: UNKNOWN
Classifier: Programming Language :: Python :: 3
Classifier: License :: OSI Approved :: GNU General Public License (GPL)
Requires-Python: >=3.6
Requires-Dist: requests
Requires-Dist: websockets
Requires-Dist: click (>=7.0)
Requires-Dist: halo
Requires-Dist: tabulate
Requires-Dist: tqdm
Requires-Dist: nest-asyncio
Requires-Dist: numpy
Requires-Dist: pyyaml
Requires-Dist: matplotlib
Requires-Dist: ipywidgets
Requires-Dist: parso (>=0.5.1)
Requires-Dist: google-resumable-media (==0.3.2)
